cryptor.py
cryptor_cli-0.1.1.dist-info/METADATA
cryptor_cli-0.1.1.dist-info/WHEEL
cryptor_cli-0.1.1.dist-info/entry_points.txt
cryptor_cli-0.1.1.dist-info/top_level.txt
cryptor_cli-0.1.1.dist-info/RECORD
