Metadata-Version: 2.4
Name: cryptor-cli
Version: 0.1.1
Summary: A CLI tool for secure file encryption using AES-256-GCM and Argon2.
Home-page: https://github.com/yourusername/cryptor-cli
Author: Your Name
Author-email: your.email@example.com
Classifier: Programming Language :: Python :: 3
Classifier: License :: OSI Approved :: MIT License
Classifier: Operating System :: OS Independent
Classifier: Development Status :: 4 - Beta
Classifier: Intended Audience :: Developers
Classifier: Intended Audience :: End Users/Desktop
Classifier: Topic :: Security :: Cryptography
Classifier: Environment :: Console
Requires-Python: >=3.7
Requires-Dist: click
Requires-Dist: cryptography
Dynamic: author
Dynamic: author-email
Dynamic: classifier
Dynamic: description
Dynamic: description-content-type
Dynamic: home-page
Dynamic: requires-dist
Dynamic: requires-python
Dynamic: summary
